aws_credentials/__init__.py
aws_credentials/cli.py
aws_credentials/manager.py
aws_credentials-0.3.0.dist-info/entry_points.txt
aws_credentials-0.3.0.dist-info/LICENSE
aws_credentials-0.3.0.dist-info/WHEEL
aws_credentials-0.3.0.dist-info/METADATA
aws_credentials-0.3.0.dist-info/RECORD
