Metadata-Version: 2.1
Name: aws-credentials
Version: 0.3.0
Summary: AWS credential manager
Home-page: https://gitlab.com/perobertson/aws-credentials
License: MIT
Keywords: access,aws,credentials,iam,rotate
Author: Paul Robertson
Author-email: t.paulrobertson@gmail.com
Requires-Python: >=3.5,<4.0
Classifier: License :: OSI Approved :: MIT License
Classifier: Programming Language :: Python :: 3
Classifier: Programming Language :: Python :: 3.5
Classifier: Programming Language :: Python :: 3.6
Classifier: Programming Language :: Python :: 3.7
Classifier: Programming Language :: Python :: 3.8
Requires-Dist: boto3 (>=1.12.37,<2.0.0)
Project-URL: Repository, https://gitlab.com/perobertson/aws-credentials
